Workbook

Sheet Dashboard
B2: 🤍 My Monthly Budget Dashboard 🤍
B4: Category | C4: Budgeted | D4: Actual
B5: Rent/Housing | C5: ='Monthly Budget'!B4 -> 150000 | D5: ='Monthly Budget'!C4 -> 150000
B6: Food & Groceries | C6: ='Monthly Budget'!B5 -> 60000 | D6: ='Monthly Budget'!C5 -> 72000
B7: Transport | C7: ='Monthly Budget'!B6 -> 25000 | D7: ='Monthly Budget'!C6 -> 28000
B8: Subscriptions | C8: ='Monthly Budget'!B7 -> 10000 | D8: ='Monthly Budget'!C7 -> 9500
B9: Skincare & Toiletries | C9: ='Monthly Budget'!B8 -> 15000 | D9: ='Monthly Budget'!C8 -> 12000
B10: Gym | C10: ='Monthly Budget'!B9 -> 8000 | D10: ='Monthly Budget'!C9 -> 6000
B11: Savings | C11: ='Monthly Budget'!B10 -> 50000 | D11: ='Monthly Budget'!C10 -> 50000
B25: 🤍 Daily Motivation 🤍
B26: Save today, enjoy tomorrow. Your future self will thank you!" ✨

Sheet Monthly Budget
B1: 📋 Monthly Budget Planner
A2: Track what you plan to spend vs what you actually spend each month 🤍
A3: Category | B3: Budgeted Amount (₦) | C3: Actual Amount (₦) | D3: Difference (₦) | E3: Status
A4: Rent/Housing | B4: 150000 | C4: 150000 | D4: =B4-C4 -> 0 | E4: =IF(D4>=0,"Within Budget ✓","Over Budget ⚠") -> Within Budget ✓
A5: Food & Groceries | B5: 60000 | C5: 72000 | D5: =B5-C5 -> -12000 | E5: =IF(D5>=0,"Within Budget ✓","Over Budget ⚠") -> Over Budget ⚠
A6: Transport | B6: 25000 | C6: 28000 | D6: =B6-C6 -> -3000 | E6: =IF(D6>=0,"Within Budget ✓","Over Budget ⚠") -> Over Budget ⚠
A7: Subscriptions | B7: 10000 | C7: 9500 | D7: =B7-C7 -> 500 | E7: =IF(D7>=0,"Within Budget ✓","Over Budget ⚠") -> Within Budget ✓
A8: Skincare & Toiletries | B8: 15000 | C8: 12000 | D8: =B8-C8 -> 3000 | E8: =IF(D8>=0,"Within Budget ✓","Over Budget ⚠") -> Within Budget ✓
A9: Gym | B9: 8000 | C9: 6000 | D9: =B9-C9 -> 2000 | E9: =IF(D9>=0,"Within Budget ✓","Over Budget ⚠") -> Within Budget ✓
A10: Savings Goal | B10: 50000 | C10: 50000 | D10: =B10-C10 -> 0 | E10: =IF(D10>=0,"Within Budget ✓","Over Budget ⚠") -> Within Budget ✓
A11: TOTAL INCOME | B11: 400000
A12: TOTALS | B12: =SUM(B4:B10) -> 318000 | C12: =SUM(C4:C10) -> 327500 | D12: =SUM(D4:D10) -> -9500 | E12: Review Spending
A13: REMAINING BALANCE | D13: =B11-C12 -> 72500

Sheet Expense Tracker
A1: 💳 Expense Tracker | G1: 📊 Quick Stats
A2: Record every naira you spend. Small amounts add up! 🤍
A3: Date | B3: Category | C3: Description | D3: Amount (₦) | E3: Payment Method | G3: Total Spent | H3: =SUM(D4:D15) -> 60000
A4: 46024 | B4: Food & Groceries | C4: Groceries from market | D4: 8500 | E4: Cash | G4: Number of Transactions | H4: =COUNT(D4:D15) -> 12
A5: 46027 | B5: Transport | C5: Fuel | D5: 2500 | E5: Transfer | G5: Lowest Single Expense | H5: =MIN(D4:D15) -> 2500
A6: 46032 | B6: Subscriptions | C6: Data bundle | D6: 5000 | E6: Transfer | G6: Highest Single Expense | H6: =MAX(D4:D15) -> 9000
A7: 46032 | B7: Gym | C7: Monthly membership | D7: 4500 | E7: Card | G7: Average per Transaction | H7: =H3/H4 -> 5000
A8: 46037 | B8: Skincare & Toiletries | C8: Skincare products | D8: 3000 | E8: Transfer
A9: 46038 | B9: Subscriptions | C9: Netflix | D9: 6000 | E9: Card
A10: 46039 | B10: Food & Groceries | C10: Market run | D10: 5000 | E10: Cash
A11: 46040 | B11: Transport | C11: Uber rides | D11: 3500 | E11: Card
A12: 46041 | B12: Skincare & Toiletries | C12: Hair products | D12: 3500 | E12: Card
A13: 46042 | B13: Subscriptions | C13: Spotify premium | D13: 3500 | E13: Card
A14: 46043 | B14: Transport | C14: Uber rides | D14: 6000 | E14: Transfer
A15: 46044 | B15: Food & Groceries | C15: Supermarket run | D15: 9000 | E15: Cash
A16: TOTAL | D16: =SUM(D4:D15) -> 60000
